NPCAnalysis/Custom.txt
NPCAnalysis/Default_Analysis_Info.txt
NPCAnalysis/Help.txt
NPCAnalysis/__init__.py
NPCAnalysis/__main__.py
npc_analyze_image-1.0.1.dist-info/LICENSE
npc_analyze_image-1.0.1.dist-info/METADATA
npc_analyze_image-1.0.1.dist-info/WHEEL
npc_analyze_image-1.0.1.dist-info/top_level.txt
npc_analyze_image-1.0.1.dist-info/RECORD
