Metadata-Version: 2.1
Name: npc-analyze-image
Version: 1.0.1
Summary: A Python package to assist in performing image analysis on Neural Progenitor Cells (NPCS).
Home-page: https://github.com/Anhardy1999/NPC_Image_Analysis
Author: Ashley Hardy
Author-email: ahardy.contact@gmail.com
Project-URL: Bug Tracker, https://github.com/Anhardy1999/NPC_Image_Analysis/issues
Classifier: Programming Language :: Python :: 3
Classifier: License :: OSI Approved :: MIT License
Classifier: Operating System :: OS Independent
Requires-Python: >=3.6
License-File: LICENSE
